octodns_yamlimproved/__init__.py
octodns_yamlimproved-0.0.2.dist-info/METADATA
octodns_yamlimproved-0.0.2.dist-info/WHEEL
octodns_yamlimproved-0.0.2.dist-info/top_level.txt
octodns_yamlimproved-0.0.2.dist-info/RECORD
