Metadata-Version: 2.1
Name: octodns-yamlimproved
Version: 0.0.2
Summary: YAMLimproved provider for octoDNS
Home-page: https://github.com/junnhy5/octodns-yamlimproved
Author: Julien Briault
Author-email: jbriault@deezer.com
License: MIT
Requires-Python: >=3.6
Requires-Dist: octodns (>=0.9.14)
Provides-Extra: dev
Requires-Dist: pytest ; extra == 'dev'
Requires-Dist: pytest-cov ; extra == 'dev'
Requires-Dist: pytest-network ; extra == 'dev'
Requires-Dist: black (>=22.3.0) ; extra == 'dev'
Requires-Dist: build (>=0.7.0) ; extra == 'dev'
Requires-Dist: pyflakes (>=2.2.0) ; extra == 'dev'
Requires-Dist: readme-renderer[md] (>=26.0) ; extra == 'dev'
Requires-Dist: twine (>=3.4.2) ; extra == 'dev'
Provides-Extra: test
Requires-Dist: pytest ; extra == 'test'
Requires-Dist: pytest-cov ; extra == 'test'
Requires-Dist: pytest-network ; extra == 'test'
